snownlp/__init__.py
snownlp/classification/__init__.py
snownlp/classification/bayes.py
snownlp/normal/__init__.py
snownlp/normal/pinyin.py
snownlp/normal/pinyin.txt
snownlp/normal/stopwords.txt
snownlp/normal/zh.py
snownlp/seg/__init__.py
snownlp/seg/data.txt
snownlp/seg/seg.marshal
snownlp/seg/seg.marshal.3
snownlp/seg/seg.py
snownlp/seg/y09_2047.py
snownlp/sentiment/__init__.py
snownlp/sentiment/neg.txt
snownlp/sentiment/pos.txt
snownlp/sentiment/sentiment.marshal
snownlp/sentiment/sentiment.marshal.3
snownlp/sim/__init__.py
snownlp/sim/bm25.py
snownlp/summary/__init__.py
snownlp/summary/textrank.py
snownlp/summary/words_merge.py
snownlp/tag/199801.txt
snownlp/tag/__init__.py
snownlp/tag/tag.marshal
snownlp/tag/tag.marshal.3
snownlp/utils/__init__.py
snownlp/utils/frequency.py
snownlp/utils/good_turing.py
snownlp/utils/tnt.py
snownlp/utils/trie.py
snownlp_pro-1.12.3.dist-info/LICENSE
snownlp_pro-1.12.3.dist-info/LICENSE.md
snownlp_pro-1.12.3.dist-info/METADATA
snownlp_pro-1.12.3.dist-info/WHEEL
snownlp_pro-1.12.3.dist-info/top_level.txt
snownlp_pro-1.12.3.dist-info/RECORD
